{
  "manifest": {
    "apis": {
      "custom": {
        "endpoint": {
          "uri": "arn:aws:lambda:us-east-1:934108339803:function:c44a520d-9d93-42d8-8e6e-4fa3d3ae1a62:Release_0"
        },
        "interfaces": []
      }
    },
    "manifestVersion": "1.0",
    "publishingInformation": {
      "category": "KNOWLEDGE_AND_TRIVIA",
      "distributionCountries": [],
      "isAvailableWorldwide": true,
      "locales": {
        "pt-BR": {
          "description": "Sample Full Description",
          "examplePhrases": [
            "Alexa open hello world",
            "hello",
            "help"
          ],
          "keywords": [],
          "name": "Cake Walk",
          "summary": "Sample Short Description"
        }
      },
      "testingInstructions": "Sample Testing Instructions."
    }
  }
}